{
  "StreamConfig": {},
  "State": {
    "Running": false,
    "Paused": false,
    "Restarting": false,
    "OOMKilled": false,
    "RemovalInProgress": false,
    "Dead": false,
    "Pid": 2,
    "ExitCode": 0,
    "Error": "",
    "StartedAt": "2022-09-28T01:54:17.617803777Z",
    "FinishedAt": "2022-09-28T01:54:33.381733213Z",
    "Health": null
  },
  "ID": "1e174614a7bd08ac0b6df67986bb1bdf33a5b84ec413c0264e05d1a69087ba96",
  "Created": "2022-09-28T01:49:04.222129394Z",
  "Managed": false,
  "Path": "docker-entrypoint.sh",
  "Args": ["postgres"],
  "Config": {
    "Hostname": "1e174614a7bd",
    "Domainname": "",
    "User": "",
    "AttachStdin": false,
    "AttachStdout": false,
    "AttachStderr": false,
    "ExposedPorts": { "5432/tcp": {} },
    "Tty": false,
    "OpenStdin": false,
    "StdinOnce": false,
    "Env": [
      "POSTGRES_PASSWORD=bYLrm2ad33B83by76N7EqqGL",
      "PATH=/usr/local/sbin:/usr/local/bin:/usr/sbin:/usr/bin:/sbin:/bin:/usr/lib/postgresql/14/bin",
      "GOSU_VERSION=1.14",
      "LANG=en_US.utf8",
      "PG_MAJOR=14",
      "PG_VERSION=14.5-1.pgdg110+1",
      "PGDATA=/var/lib/postgresql/data"
    ],
    "Cmd": ["postgres"],
    "Image": "postgres",
    "Volumes": { "/var/lib/postgresql/data": {} },
    "WorkingDir": "",
    "Entrypoint": ["docker-entrypoint.sh"],
    "OnBuild": null,
    "Labels": {},
    "StopSignal": "SIGINT"
  },
  "Image": "sha256:75993dd36176c7d4be8c1e6d88a115f1fb35a85451088699dbdc80659ad688ed",
  "NetworkSettings": {
    "Bridge": "",
    "SandboxID": "4835fcf0d0aa48633aa26e6d74e9e9713a044175e9b1f8ce72cd14101ca96bb9",
    "HairpinMode": false,
    "LinkLocalIPv6Address": "",
    "LinkLocalIPv6PrefixLen": 0,
    "Networks": {
      "bridge": {
        "IPAMConfig": null,
        "Links": null,
        "Aliases": null,
        "NetworkID": "e340e970a16fb7cd2ce119c29ae69856ea23d223e05cb070b2edf0a957e811fe",
        "EndpointID": "",
        "Gateway": "",
        "IPAddress": "",
        "IPPrefixLen": 0,
        "IPv6Gateway": "",
        "GlobalIPv6Address": "",
        "GlobalIPv6PrefixLen": 0,
        "MacAddress": "",
        "DriverOpts": null,
        "IPAMOperational": false
      }
    },
    "Service": null,
    "Ports": null,
    "SandboxKey": "/var/run/docker/netns/4835fcf0d0aa",
    "SecondaryIPAddresses": null,
    "SecondaryIPv6Addresses": null,
    "IsAnonymousEndpoint": false,
    "HasSwarmEndpoint": false
  },
  "LogPath": "/var/lib/docker/containers/1e174614a7bd08ac0b6df67986bb1bdf33a5b84ec413c0264e05d1a69087ba96/1e174614a7bd08ac0b6df67986bb1bdf33a5b84ec413c0264e05d1a69087ba96-json.log",
  "Name": "/econdb",
  "Driver": "overlay2",
  "OS": "linux",
  "MountLabel": "",
  "ProcessLabel": "",
  "RestartCount": 0,
  "HasBeenStartedBefore": true,
  "HasBeenManuallyStopped": true,
  "MountPoints": {
    "/var/lib/postgresql/data": {
      "Source": "",
      "Destination": "/var/lib/postgresql/data",
      "RW": true,
      "Name": "6db53e77b63655cbfb5043049caeca05e93ee04ce27769ae7f4cfafdbd5353bc",
      "Driver": "local",
      "Type": "volume",
      "Spec": {},
      "SkipMountpointCreation": false
    }
  },
  "SecretReferences": null,
  "ConfigReferences": null,
  "AppArmorProfile": "docker-default",
  "HostnamePath": "/var/lib/docker/containers/1e174614a7bd08ac0b6df67986bb1bdf33a5b84ec413c0264e05d1a69087ba96/hostname",
  "HostsPath": "/var/lib/docker/containers/1e174614a7bd08ac0b6df67986bb1bdf33a5b84ec413c0264e05d1a69087ba96/hosts",
  "ShmPath": "",
  "ResolvConfPath": "/var/lib/docker/containers/1e174614a7bd08ac0b6df67986bb1bdf33a5b84ec413c0264e05d1a69087ba96/resolv.conf",
  "SeccompProfile": "",
  "NoNewPrivileges": false,
  "LocalLogCacheMeta": { "HaveNotifyEnabled": false }
}
